{
	"configurations" : 
	[
		{
			"directories" : 
			[
				{
					"build" : ".",
					"hasInstallRule" : true,
					"jsonFile" : "directory-.-6fb705d95eb9ef6bbf67.json",
					"minimumCMakeVersion" : 
					{
						"string" : "3.12"
					},
					"projectIndex" : 0,
					"source" : ".",
					"targetIndexes" : 
					[
						0,
						1
					]
				}
			],
			"name" : "",
			"projects" : 
			[
				{
					"directoryIndexes" : 
					[
						0
					],
					"name" : "bhand",
					"targetIndexes" : 
					[
						0,
						1
					]
				}
			],
			"targets" : 
			[
				{
					"directoryIndex" : 0,
					"id" : "bhand_uninstall::@6890427a1f51a3e7e1df",
					"jsonFile" : "target-bhand_uninstall-2f3beb481fb98e1cd009.json",
					"name" : "bhand_uninstall",
					"projectIndex" : 0
				},
				{
					"directoryIndex" : 0,
					"id" : "uninstall::@6890427a1f51a3e7e1df",
					"jsonFile" : "target-uninstall-578cf94b149454088aa1.json",
					"name" : "uninstall",
					"projectIndex" : 0
				}
			]
		}
	],
	"kind" : "codemodel",
	"paths" : 
	{
		"build" : "/home/fzc/allegro_hand_linux_v4/ros2_source/build/bhand",
		"source" : "/home/fzc/allegro_hand_linux_v4/ros2_source/src/bhand"
	},
	"version" : 
	{
		"major" : 2,
		"minor" : 3
	}
}
